{
  "resources": [
    {
      "path": "data.csv",
      "name": "data",
      "profile": "tabular-data-resource",
      "scheme": "file",
      "format": "csv",
      "hashing": "md5",
      "encoding": "utf-8",
      "schema": {
        "fields": [
          {
            "name": "Year",
            "type": "integer",
            "title": "Jahr"
          },
          {
            "name": "Units",
            "type": "string",
            "constraints": {
              "enum": [
                "Prozent",
                "1 000 Tonnen",
                ""
              ]
            },
            "title": "Units"
          },
          {
            "name": "timeseries",
            "type": "string",
            "constraints": {
              "enum": [
                "Recyclingquote",
                "Stoffliche Verwertung",
                ""
              ]
            },
            "title": "Zeitreihe"
          },
          {
            "name": "type of waste",
            "type": "string",
            "constraints": {
              "enum": [
                "Siedlungsabfälle insgesamt",
                "Abfallaufkommen insgesamt",
                ""
              ]
            },
            "title": "Abfallart"
          },
          {
            "name": "Value",
            "type": "integer",
            "title": "Value"
          }
        ]
      }
    }
  ],
  "profile": "data-package",
  "name": "12-5-1",
  "title": "Nationale Recyclingquote, Tonnen an recyceltem Material"
}