[{"Year":2010,"Value":15.6,"Series":"Armutsgef\u00e4hrdungsquote"},{"Year":2011,"Value":15.8,"Series":"Armutsgef\u00e4hrdungsquote"},{"Year":2012,"Value":16.1,"Series":"Armutsgef\u00e4hrdungsquote"},{"Year":2013,"Value":16.1,"Series":"Armutsgef\u00e4hrdungsquote"},{"Year":2014,"Value":16.7,"Series":"Armutsgef\u00e4hrdungsquote"},{"Year":2015,"Value":16.7,"Series":"Armutsgef\u00e4hrdungsquote"},{"Year":2016,"Value":16.5,"Series":"Armutsgef\u00e4hrdungsquote"},{"Year":2017,"Value":16.1,"Series":"Armutsgef\u00e4hrdungsquote"},{"Year":2018,"Value":16.0,"Series":"Armutsgef\u00e4hrdungsquote"},{"Year":2019,"Value":14.8,"Series":"Armutsgef\u00e4hrdungsquote"},{"Year":2021,"Value":16.0,"Series":"Armutsgef\u00e4hrdungsquote"},{"Year":2022,"Value":14.8,"Series":"Armutsgef\u00e4hrdungsquote"},{"Year":2023,"Value":14.4,"Series":"Armutsgef\u00e4hrdungsquote"}]