{"data":{"Year":[2010,2011,2012,2013,2014,2015,2016,2017,2018,2010,2013,2016,2010,2013,2016,2010,2013,2016],"Units":["%","%","%","%","%","%","%","%","%","%","%","%","%","%","%","%","%","%"],"timeseries":["wastewater safely treated","wastewater safely treated","wastewater safely treated","wastewater safely treated","wastewater safely treated","wastewater safely treated","wastewater safely treated","wastewater safely treated","wastewater safely treated","wastewater safely treated","wastewater safely treated","wastewater safely treated","wastewater safely treated","wastewater safely treated","wastewater safely treated","wastewater safely treated","wastewater safely treated","wastewater safely treated"],"type of treatment":[null,null,null,null,null,null,null,null,null,"cooling water","cooling water","cooling water","other wastewater that does not have to undergo treatment","other wastewater that does not have to undergo treatment","other wastewater that does not have to undergo treatment","untreated wastewater that does not have to undergo treatment","untreated wastewater that does not have to undergo treatment","untreated wastewater that does not have to undergo treatment"],"Value":[100.0,100.0,100.0,100.0,100.0,100.0,100.0,100.0,100.0,68.3,60.3,59.7,4.4,5.5,5.7,72.7,65.8,65.4]},"edges":{"From":["timeseries"],"To":["type of treatment"]}}