{
  "resources": [
    {
      "path": "data.csv",
      "name": "data",
      "profile": "tabular-data-resource",
      "scheme": "file",
      "format": "csv",
      "hashing": "md5",
      "encoding": "utf-8",
      "schema": {
        "fields": [
          {
            "name": "Year",
            "type": "integer",
            "title": "Jahr"
          },
          {
            "name": "Units",
            "type": "string",
            "constraints": {
              "enum": [
                "Keine Einheit",
                "Anzahl",
                ""
              ]
            },
            "title": "Units"
          },
          {
            "name": "Series",
            "type": "string",
            "constraints": {
              "enum": [
                "Vertragsparteien des Internationalen Saatgutvertrags",
                "Vertragsparteien des Nagoya-Protokoll",
                "Länder, die über gesetzliche, administrative und politische Rahmenbedingungen oder Maßnahmen verfügen, die über das Online-Berichtssystem zur Einhaltung des Internationalen Saatgutvertrag gemeldet wurden",
                "Länder, die über gesetzliche, administrative und politische Rahmenbedingungen oder Maßnahmen verfügen, die dem Access and Benefit-Sharing Clearing-House gemeldet wurden",
                "Anzahl standardisierter Materialübertragungs-vereinbarungen",
                ""
              ]
            },
            "title": "Zeitreihe"
          },
          {
            "name": "Value",
            "type": "number",
            "title": "Value"
          }
        ]
      }
    }
  ],
  "profile": "data-package",
  "name": "15-6-1",
  "title": "Anzahl der Staaten, die rechtliche, administrative und politische Rahmenbedingungen verabschiedet haben, um Vorteile gerecht und gleichmäßig zu verteilen"
}