{"data":{"Year":[2010,2011,2012,2013,2014,2015,2016,2017,2018,2019,2020,2010,2011,2012,2013,2014,2015,2016,2017,2018,2019,2020],"Zeitreihe":["Zweigstellen von Zahlungsverkehrsdienstleistern","Zweigstellen von Zahlungsverkehrsdienstleistern","Zweigstellen von Zahlungsverkehrsdienstleistern","Zweigstellen von Zahlungsverkehrsdienstleistern","Zweigstellen von Zahlungsverkehrsdienstleistern","Zweigstellen von Zahlungsverkehrsdienstleistern","Zweigstellen von Zahlungsverkehrsdienstleistern","Zweigstellen von Zahlungsverkehrsdienstleistern","Zweigstellen von Zahlungsverkehrsdienstleistern","Zweigstellen von Zahlungsverkehrsdienstleistern","Zweigstellen von Zahlungsverkehrsdienstleistern","Bankautomaten von inl\u00e4ndischen Zahlungsdienstleistern","Bankautomaten von inl\u00e4ndischen Zahlungsdienstleistern","Bankautomaten von inl\u00e4ndischen Zahlungsdienstleistern","Bankautomaten von inl\u00e4ndischen Zahlungsdienstleistern","Bankautomaten von inl\u00e4ndischen Zahlungsdienstleistern","Bankautomaten von inl\u00e4ndischen Zahlungsdienstleistern","Bankautomaten von inl\u00e4ndischen Zahlungsdienstleistern","Bankautomaten von inl\u00e4ndischen Zahlungsdienstleistern","Bankautomaten von inl\u00e4ndischen Zahlungsdienstleistern","Bankautomaten von inl\u00e4ndischen Zahlungsdienstleistern","Bankautomaten von inl\u00e4ndischen Zahlungsdienstleistern"],"Value":[56.7,57.1,54.8,54.4,52.9,48.1,44.9,42.2,39.0,37.3,33.7,116.5,121.1,118.5,118.3,123.4,122.3,132.3,132.9,134.4,122.0,122.4]},"edges":[]}